doloop.py
doloop-1.0.0.dist-info/DESCRIPTION.rst
doloop-1.0.0.dist-info/METADATA
doloop-1.0.0.dist-info/RECORD
doloop-1.0.0.dist-info/WHEEL
doloop-1.0.0.dist-info/entry_points.txt
doloop-1.0.0.dist-info/metadata.json
doloop-1.0.0.dist-info/top_level.txt
